blendedUxLang/__init__.py
blendedUxLang/blended/__init__.py
blendedUxLang/blended/_compat.py
blendedUxLang/blended/colormap.py
blendedUxLang/blended/flask.py
blendedUxLang/blended/functions.py
blendedUxLang/blended/jinjaenv.py
blendedUxLang/blended/sets.py
blendedUxLang/blended/trimfloat.py
blendedUxLang/blended/djangolint/__init__.py
blendedUxLang/blended/djangolint/admin.py
blendedUxLang/blended/djangolint/models.py
blendedUxLang/blended/djangolint/tests.py
blendedUxLang/blended/djangolint/urls.py
blendedUxLang/blended/djangolint/views.py
blendedUxLang/blended/djangolint/migrations/__init__.py
blendedUxLang/blended/djangotags/__init__.py
blendedUxLang/blended/djangotags/jinjaenv.py
blendedUxLang/blended/djangotags/loader.py
blendedUxLang/blended/djangotags/models.py
blendedUxLang/blended/djangotags/tests.py
blendedUxLang/blended/djangotags/templatetags/__init__.py
blendedUxLang/blended/djangotags/templatetags/blended_tags.py
blendedUxLang/blended/lint/__init__.py
blendedUxLang/blended/lint/lint.py
blendedUxLang/blended/lint/lintcommands.py
blendedUxLang/blended/lint/listeners.py
blendedUxLang/blended/lint/blended_grammar/__init__.py
blendedUxLang/blended/lint/blended_grammar/blendedParserListener.py
blendedUxLang/blended/lint/blended_grammar/py2/__init__.py
blendedUxLang/blended/lint/blended_grammar/py2/blendedLexer.py
blendedUxLang/blended/lint/blended_grammar/py2/blendedParser.py
blendedUxLang/blended/lint/blended_grammar/py3/__init__.py
blendedUxLang/blended/lint/blended_grammar/py3/blendedLexer.py
blendedUxLang/blended/lint/blended_grammar/py3/blendedParser.py
sunny2_blended_lang-0.0.1.dist-info/LICENSE
sunny2_blended_lang-0.0.1.dist-info/METADATA
sunny2_blended_lang-0.0.1.dist-info/WHEEL
sunny2_blended_lang-0.0.1.dist-info/top_level.txt
sunny2_blended_lang-0.0.1.dist-info/RECORD
