Metadata-Version: 2.1
Name: sunny2-blended-lang
Version: 0.0.1
Summary: Test package
Home-page: UNKNOWN
Author: sunny
Author-email: <sprakash@cognam.com>
License: UNKNOWN
Platform: UNKNOWN
Requires-Dist: markupsafe
